{
  "id": "shakai-koumin-01",
  "subject": "shakai",
  "section": "koumin",
  "title": "公民クイズ",
  "createdAt": "2026-06-20",
  "questions": [
    {
      "id": "q1",
      "question": "日本国憲法第 25 条で定められている、健康で文化的な最低限度の生活を営む権利を何といいますか。",
      "choices": [
        "生存権",
        "自由権",
        "参政権",
        "平等権"
      ],
      "answerIndex": 0,
      "explanation": "日本国憲法第 25 条はすべての国民に生存権を保障しており、これに基づき社会保障制度が運営されています。"
    },
    {
      "id": "q2",
      "question": "社会保障の「四つの柱」のうち、感染症の予防や保健所による環境衛生の整備を行うものを何といいますか。",
      "choices": [
        "社会福祉",
        "公的扶助",
        "社会保険",
        "公衆衛生"
      ],
      "answerIndex": 3,
      "explanation": "国民全体の健康維持を目的として、感染症対策や地域の環境衛生を整える制度です。"
    },
    {
      "id": "q3",
      "question": "家族の介護や世話を日常的に行い、自分の時間が取れないなどの負担を抱えている子供を何といいますか。",
      "choices": [
        "ケアマネージャー",
        "ヤングケアラー",
        "ホームヘルパー",
        "ボランティア"
      ],
      "answerIndex": 1,
      "explanation": "本来大人が行うような家事や介護を日常的に担っている 18 歳未満の子供を指します。"
    },
    {
      "id": "q4",
      "question": "所得が高い人ほど、より高い税率が適用される課税制度を何といいますか。",
      "choices": [
        "一律課税制度",
        "軽減税率制度",
        "累進課税制度",
        "逆進課税制度"
      ],
      "answerIndex": 2,
      "explanation": "所得が多い人ほど税金の負担能力が高いと考え、段階的に高い税率を課す所得税などの仕組みです。"
    },
    {
      "id": "q5",
      "question": "国の歳入において、税収だけで足りない場合に発行する、将来返済が必要な「国の借金」を何といいますか。",
      "choices": [
        "国債",
        "地方交付税",
        "直接税",
        "剰余金"
      ],
      "answerIndex": 0,
      "explanation": "国が資金を調達するために発行する債券であり、歳入項目では公債金として計上されます。"
    },
    {
      "id": "q6",
      "question": "「日本銀行」が行っている、景気を調整するための役割として正しくないものはどれですか。",
      "choices": [
        "紙幣（日本銀行券）を発行する。",
        "公共事業の内容を決定し、実行する。",
        "一般の銀行にお金を貸し出す。",
        "国の予算や税金を管理する。"
      ],
      "answerIndex": 1,
      "explanation": "公共事業の決定や実行は政府（内閣）や地方公共団体が行う財政政策の範囲です。"
    },
    {
      "id": "q7",
      "question": "物価が下がり続け、お金の価値が上がっていく現象を何といいますか。",
      "choices": [
        "インフレーション",
        "円高",
        "スタグフレーション",
        "デフレーション"
      ],
      "answerIndex": 3,
      "explanation": "需要が供給を下回り、物価が持続的に下落する現象を指します。"
    },
    {
      "id": "q8",
      "question": "発展途上国で作られた農産物や製品を、適正な価格で購入することで生産者の生活を支える仕組みを何といいますか。",
      "choices": [
        "自由貿易",
        "保護貿易",
        "フェアトレード",
        "加工貿易"
      ],
      "answerIndex": 2,
      "explanation": "公正（フェア）な取引（トレード）を行うことで、途上国の労働者の自立を支援する国際的な取り組みです。"
    },
    {
      "id": "q9",
      "question": "経済のグローバル化の中で、特定の国や地域の間で関税をなくし、幅広い経済連携を図る協定を何といいますか。",
      "choices": [
        "WTO",
        "EPA",
        "G7",
        "NPO"
      ],
      "answerIndex": 1,
      "explanation": "経済連携協定（Economic Partnership Agreement）の略で、関税撤廃だけでなく投資や人の移動も含む幅広い連携を指します。"
    },
    {
      "id": "q10",
      "question": "先進国（北半球に多い）と発展途上国（南半球に多い）との間の経済格差から生じる問題を何といいますか。",
      "choices": [
        "南北問題",
        "南南問題",
        "冷戦問題",
        "貿易摩擦"
      ],
      "answerIndex": 0,
      "explanation": "豊かな先進工業国が北側に、発展途上国が南側に多く分布していることからこのように呼ばれます。"
    }
  ]
}
